Metadata-Version: 1.1
Name: aprdna
Version: 0.1.0
Summary: Analizer of periodic repetitions in DNA
Home-page: UNKNOWN
Author: Enrique Pérez
Author-email: enriquepablo@gmail.com
License: bsd
Platform: UNKNOWN
Classifier: Programming Language :: Python
